package/main.py
package/assets/__init__.py
package/components/__init__.py
package/components/model.py
package/layout/__init__.py
package/layout/layout.py
package/utils/__init__.py
package/utils/constraints.py
package/utils/functions.py
package/utils/get_master_data.py
isv3-0.0.1.dist-info/LICENSE
isv3-0.0.1.dist-info/METADATA
isv3-0.0.1.dist-info/WHEEL
isv3-0.0.1.dist-info/top_level.txt
isv3-0.0.1.dist-info/RECORD
